Metadata-Version: 2.1
Name: volume-segmantics
Version: 0.3.2
Summary: A toolkit for semantic segmentation of volumetric data using pyTorch deep learning models
Home-page: https://github.com/DiamondLightSource/volume-segmantics
License: Apache-2.0
Keywords: segmentation,deep-learning,volumetric,3d
Author: Oliver King
Author-email: olly.king@diamond.ac.uk
Requires-Python: >=3.7,<4.0
Classifier: Development Status :: 5 - Production/Stable
Classifier: Intended Audience :: Science/Research
Classifier: License :: OSI Approved :: Apache Software License
Classifier: Operating System :: OS Independent
Classifier: Programming Language :: Python :: 3
Classifier: Programming Language :: Python :: 3.7
Classifier: Programming Language :: Python :: 3.8
Classifier: Programming Language :: Python :: 3.9
Classifier: Programming Language :: Python :: 3.10
Classifier: Programming Language :: Python :: 3.11
Classifier: Topic :: Scientific/Engineering :: Image Processing
Requires-Dist: albumentations (>=1.1.0,<2.0.0)
Requires-Dist: h5py (>=3.0.0,<4.0.0)
Requires-Dist: imagecodecs
Requires-Dist: matplotlib (>=3.3.0,<4.0.0)
Requires-Dist: numpy (>=1.18.0,<2.0.0)
Requires-Dist: segmentation-models-pytorch (>=0.2.1,<0.3.0)
Requires-Dist: termplotlib (>=0.3.6,<0.4.0)
Requires-Dist: torch (>=1.7.1)
Project-URL: Repository, https://github.com/DiamondLightSource/volume-segmantics
